{
  "salary": 121000,
  "gross_salary": 121000,
  "state": "Washington, D.C.",
  "state_code": "DC",
  "filing_status": "Single",
  "tax_year": 2026,
  "estimate_type": "projected",
  "federal_tax": 18191,
  "state_tax": 7508,
  "social_security": 7502,
  "medicare": 1755,
  "medicare_surtax": 0,
  "total_tax": 34956,
  "effective_tax_rate": 28.89,
  "net_salary": 86044,
  "monthly_take_home": 7170,
  "biweekly_take_home": 3309,
  "benefits": {
    "employer_401k_match": 3630,
    "health_insurance_value": 6000
  },
  "total_compensation": 130630
}