{
  "salary": 186000,
  "gross_salary": 186000,
  "state": "Illinois",
  "state_code": "IL",
  "filing_status": "Single",
  "tax_year": 2026,
  "estimate_type": "projected",
  "federal_tax": 33791,
  "state_tax": 9207,
  "social_security": 10329,
  "medicare": 2697,
  "medicare_surtax": 0,
  "total_tax": 56024,
  "effective_tax_rate": 30.12,
  "net_salary": 129976,
  "monthly_take_home": 10831,
  "biweekly_take_home": 4999,
  "benefits": {
    "employer_401k_match": 5580,
    "health_insurance_value": 6000
  },
  "total_compensation": 197580
}