{
  "salary": 229000,
  "gross_salary": 229000,
  "state": "Massachusetts",
  "state_code": "MA",
  "filing_status": "Single",
  "tax_year": 2026,
  "estimate_type": "projected",
  "federal_tax": 45387,
  "state_tax": 11450,
  "social_security": 10329,
  "medicare": 3321,
  "medicare_surtax": 261,
  "total_tax": 70748,
  "effective_tax_rate": 30.89,
  "net_salary": 158252,
  "monthly_take_home": 13188,
  "biweekly_take_home": 6087,
  "benefits": {
    "employer_401k_match": 6870,
    "health_insurance_value": 6000
  },
  "total_compensation": 241870
}