{
  "salary": 281000,
  "gross_salary": 281000,
  "state": "New Jersey",
  "state_code": "NJ",
  "filing_status": "Single",
  "tax_year": 2026,
  "estimate_type": "projected",
  "federal_tax": 62467,
  "state_tax": 15773,
  "social_security": 10329,
  "medicare": 4075,
  "medicare_surtax": 729,
  "total_tax": 93373,
  "effective_tax_rate": 33.23,
  "net_salary": 187627,
  "monthly_take_home": 15636,
  "biweekly_take_home": 7216,
  "benefits": {
    "employer_401k_match": 8430,
    "health_insurance_value": 6000
  },
  "total_compensation": 295430
}