{
  "salary": 332000,
  "gross_salary": 332000,
  "state": "Virginia",
  "state_code": "VA",
  "filing_status": "Single",
  "tax_year": 2026,
  "estimate_type": "projected",
  "federal_tax": 80317,
  "state_tax": 19090,
  "social_security": 10329,
  "medicare": 4814,
  "medicare_surtax": 1188,
  "total_tax": 115738,
  "effective_tax_rate": 34.86,
  "net_salary": 216262,
  "monthly_take_home": 18022,
  "biweekly_take_home": 8318,
  "benefits": {
    "employer_401k_match": 9960,
    "health_insurance_value": 6000
  },
  "total_compensation": 347960
}