{
  "salary": 395000,
  "gross_salary": 395000,
  "state": "Minnesota",
  "state_code": "MN",
  "filing_status": "Single",
  "tax_year": 2026,
  "estimate_type": "projected",
  "federal_tax": 102367,
  "state_tax": 32202,
  "social_security": 10329,
  "medicare": 5728,
  "medicare_surtax": 1755,
  "total_tax": 152381,
  "effective_tax_rate": 38.58,
  "net_salary": 242619,
  "monthly_take_home": 20218,
  "biweekly_take_home": 9332,
  "benefits": {
    "employer_401k_match": 11850,
    "health_insurance_value": 6000
  },
  "total_compensation": 412850
}