{
  "salary": 488000,
  "gross_salary": 488000,
  "state": "Washington, D.C.",
  "state_code": "DC",
  "filing_status": "Single",
  "tax_year": 2026,
  "estimate_type": "projected",
  "federal_tax": 134917,
  "state_tax": 43746,
  "social_security": 10329,
  "medicare": 7076,
  "medicare_surtax": 2592,
  "total_tax": 198660,
  "effective_tax_rate": 40.71,
  "net_salary": 289340,
  "monthly_take_home": 24112,
  "biweekly_take_home": 11128,
  "benefits": {
    "employer_401k_match": 14640,
    "health_insurance_value": 6000
  },
  "total_compensation": 508640
}