{
  "salary": 242000,
  "gross_salary": 242000,
  "state": "Pennsylvania",
  "state_code": "PA",
  "filing_status": "Single",
  "tax_year": 2025,
  "federal_tax": 50359,
  "state_tax": 7429,
  "social_security": 9932,
  "medicare": 3509,
  "medicare_surtax": 378,
  "total_tax": 71607,
  "effective_tax_rate": 29.59,
  "net_salary": 170393,
  "monthly_take_home": 14199,
  "biweekly_take_home": 6554,
  "benefits": {
    "employer_401k_match": 7260,
    "health_insurance_value": 6000
  },
  "total_compensation": 255260
}