{
  "salary": 343000,
  "gross_salary": 343000,
  "state": "Washington",
  "state_code": "WA",
  "filing_status": "Single",
  "tax_year": 2025,
  "federal_tax": 85210,
  "state_tax": 0,
  "social_security": 9932,
  "medicare": 4974,
  "medicare_surtax": 1287,
  "total_tax": 101403,
  "effective_tax_rate": 29.56,
  "net_salary": 241597,
  "monthly_take_home": 20133,
  "biweekly_take_home": 9292,
  "benefits": {
    "employer_401k_match": 10290,
    "health_insurance_value": 6000
  },
  "total_compensation": 359290
}