{
  "salary": 380000,
  "gross_salary": 380000,
  "state": "Colorado",
  "state_code": "CO",
  "filing_status": "Single",
  "tax_year": 2025,
  "federal_tax": 98160,
  "state_tax": 16720,
  "social_security": 9932,
  "medicare": 5510,
  "medicare_surtax": 1620,
  "total_tax": 131942,
  "effective_tax_rate": 34.72,
  "net_salary": 248058,
  "monthly_take_home": 20672,
  "biweekly_take_home": 9541,
  "benefits": {
    "employer_401k_match": 11400,
    "health_insurance_value": 6000
  },
  "total_compensation": 397400
}