{
  "salary": 417000,
  "gross_salary": 417000,
  "state": "Washington, D.C.",
  "state_code": "DC",
  "filing_status": "Single",
  "tax_year": 2025,
  "federal_tax": 111110,
  "state_tax": 36114,
  "social_security": 9932,
  "medicare": 6047,
  "medicare_surtax": 1953,
  "total_tax": 165156,
  "effective_tax_rate": 39.61,
  "net_salary": 251844,
  "monthly_take_home": 20987,
  "biweekly_take_home": 9686,
  "benefits": {
    "employer_401k_match": 12510,
    "health_insurance_value": 6000
  },
  "total_compensation": 435510
}