{
  "salary": 43000,
  "gross_salary": 43000,
  "state": "Pennsylvania",
  "state_code": "PA",
  "filing_status": "Single",
  "tax_year": 2025,
  "federal_tax": 3140,
  "state_tax": 1320,
  "social_security": 2666,
  "medicare": 624,
  "medicare_surtax": 0,
  "total_tax": 7750,
  "effective_tax_rate": 18.02,
  "net_salary": 35250,
  "monthly_take_home": 2938,
  "biweekly_take_home": 1356,
  "benefits": {
    "employer_401k_match": 1290,
    "health_insurance_value": 6000
  },
  "total_compensation": 50290
}