{
  "salary": 482000,
  "gross_salary": 482000,
  "state": "Minnesota",
  "state_code": "MN",
  "filing_status": "Single",
  "tax_year": 2025,
  "federal_tax": 133860,
  "state_tax": 40771,
  "social_security": 9932,
  "medicare": 6989,
  "medicare_surtax": 2538,
  "total_tax": 194090,
  "effective_tax_rate": 40.27,
  "net_salary": 287910,
  "monthly_take_home": 23993,
  "biweekly_take_home": 11073,
  "benefits": {
    "employer_401k_match": 14460,
    "health_insurance_value": 6000
  },
  "total_compensation": 502460
}