{
  "salary": 55000,
  "gross_salary": 55000,
  "state": "New Jersey",
  "state_code": "NJ",
  "filing_status": "Single",
  "tax_year": 2025,
  "federal_tax": 4580,
  "state_tax": 1546,
  "social_security": 3410,
  "medicare": 798,
  "medicare_surtax": 0,
  "total_tax": 10334,
  "effective_tax_rate": 18.79,
  "net_salary": 44666,
  "monthly_take_home": 3722,
  "biweekly_take_home": 1718,
  "benefits": {
    "employer_401k_match": 1650,
    "health_insurance_value": 6000
  },
  "total_compensation": 62650
}