{
  "salary": 57000,
  "gross_salary": 57000,
  "state": "Minnesota",
  "state_code": "MN",
  "filing_status": "Single",
  "tax_year": 2025,
  "federal_tax": 4820,
  "state_tax": 2485,
  "social_security": 3534,
  "medicare": 827,
  "medicare_surtax": 0,
  "total_tax": 11666,
  "effective_tax_rate": 20.47,
  "net_salary": 45334,
  "monthly_take_home": 3778,
  "biweekly_take_home": 1744,
  "benefits": {
    "employer_401k_match": 1710,
    "health_insurance_value": 6000
  },
  "total_compensation": 64710
}